Workbook

Sheet Instructions
B2: Turo Fleet Command Center
B3: Profitability tracker for your Tesla Model Y fleet on the Turo app
B6: HOW THIS WORKBOOK WORKS
B7: 1. Vehicles tab | C7: One row per car with fixed info (purchase price, financing, insurance, renewal dates). Update odometer/maintenance fields periodically.
B8: 2. Trips tab | C8: Log every booking. Fastest way: export your trip history / payout history from the Turo app and paste the values into the blue-font columns (Trip ID, Vehicle, dates, earnings, miles).
B9: 3. Expenses tab | C9: Log every cost as it happens: loan/lease payments, insurance, maintenance, tires, cleaning, registration, subscriptions, damage claims, misc.
B10: 4. Charging tab | C10: Log charging sessions (home electricity or public/Supercharger). This is what feeds true cost-per-mile.
B11: 5. Summary tab | C11: Everything else is computed automatically with formulas — don't type numbers there. This is your profitability command center: per-car and fleet-wide.
B13: KEEPING THE DASHBOARD UPDATED
B14: Weekly | C14: Add new trips + any new expenses/charging sessions.
B15: Monthly | C15: Reconcile against your Turo payout statements and bank/credit card statement.
B16: For the HTML Command Center dashboard | C16: Export each tab as CSV (File > Download > CSV, one file per tab: Vehicles, Trips, Expenses, Charging) and upload them into the dashboard's 'Update Data' panel. It recalculates everything client-side and remembers your last upload.
B18: COLOR KEY
B19: Blue text | C19: Type your own data here.
B20: Black text | C20: Formula — do not overwrite.
B21: Pale yellow row | C21: Example row showing expected format — delete or overwrite it once you add real data.

Sheet Vehicles
A1: Vehicle ID | B1: VIN | C1: In-Service Date | D1: Purchase Price | E1: Financing Type | F1: Monthly Loan/Lease Payment | G1: Loan Balance Remaining | H1: Monthly Insurance Premium | I1: Annual Registration/Tax | J1: Turo Commission Rate (Protection Plan) | K1: Current Odometer (mi) | L1: Next Maintenance Due (mi) | M1: Next Maintenance Due (date) | N1: Tire Replacement Due (mi) | O1: Insurance Renewal Date | P1: Registration Renewal Date | Q1: Status
A2: Model Y #1 - White | B2: 5YJYGDEE1NF000001 | C2: 2024-03-01 | D2: 52000 | E2: Loan | F2: 850 | G2: 31000 | H2: 180 | I2: 420 | J2: 0.25 | K2: 28500 | L2: 35000 | M2: 2026-09-01 | N2: 40000 | O2: 2027-03-01 | P2: 2027-03-01 | Q2: Active
A3: Model Y #2 - Black | B3: 5YJYGDEE2NF000002 | C3: 2024-06-15 | D3: 54000 | E3: Cash | F3: 0 | G3: 0 | H3: 175 | I3: 420 | J3: 0.25 | K3: 21000 | L3: 30000 | M3: 2026-08-15 | N3: 40000 | O3: 2027-06-15 | P3: 2027-06-15 | Q3: Active

Sheet Trips
A1: Trip ID | B1: Vehicle | C1: Guest Name | D1: Trip Start Date | E1: Trip End Date | F1: Trip Days | G1: Guest Trip Price ($) | H1: Host Net Earnings ($) | I1: Turo Fee ($) | J1: Miles Driven | K1: Trip Rating (1-5) | L1: Month | M1: Notes
A2: TR-1001 | B2: Model Y #1 - White | C2: Jordan P. | D2: 2026-06-02 | E2: 2026-06-05 | F2: =E2-D2+1 -> 4 | G2: 480 | H2: 360 | I2: =IF(G2=0,"",G2-H2) -> 120 | J2: 210 | K2: 5 | L2: =TEXT(D2,"yyyy-mm") -> 2026-06 | M2: Airport pickup

Sheet Expenses
A1: Date | B1: Vehicle | C1: Category | D1: Description | E1: Amount ($) | F1: Month | G1: Notes
A2: 2026-06-01 | B2: Model Y #1 - White | C2: Loan/Lease Payment | D2: June loan payment | E2: 850 | F2: =TEXT(A2,"yyyy-mm") -> 2026-06

Sheet Charging
A1: Date | B1: Vehicle | C1: Location Type | D1: kWh Added | E1: Cost ($) | F1: Cost per kWh | G1: Odometer at Charge (mi) | H1: Month | I1: Notes
A2: 2026-06-03 | B2: Model Y #1 - White | C2: Supercharger | D2: 42 | E2: 18.9 | F2: =IF(D2=0,"",E2/D2) -> 0.45 | G2: 28650 | H2: =TEXT(A2,"yyyy-mm") -> 2026-06

Sheet Summary
B1: Turo Fleet Command Center — Summary
B2: Every cell below is a formula pulling from Vehicles / Trips / Expenses / Charging. Don't type values here.
B4: FLEET KPI OVERVIEW
B6: Vehicle | C6: Days in Service | D6: Total Trips | E6: Booked Days | F6: Utilization % | G6: Gross Guest Revenue | H6: Host Net Earnings | I6: Turo Fees | J6: Avg Daily Rate | K6: Total Miles | L6: Charging Cost | M6: Cost/Mile (energy) | N6: Fixed Costs | O6: Variable Costs | P6: Total Costs | Q6: Net Profit | R6: Net Margin % | S6: Profit/Available Day | T6: Break-even Utilization %
B7: =Vehicles!A2 -> Model Y #1 - White | C7: =TODAY()-Vehicles!C2 -> 871 | D7: =COUNTIF(Trips!$B$2:$B$2000,B7) -> 1 | E7: =SUMIF(Trips!$B$2:$B$2000,B7,Trips!$F$2:$F$2000) -> 4 | F7: =IFERROR(E7/C7,0) -> 0.0045924225 | G7: =SUMIF(Trips!$B$2:$B$2000,B7,Trips!$G$2:$G$2000) -> 480 | H7: =SUMIF(Trips!$B$2:$B$2000,B7,Trips!$H$2:$H$2000) -> 360 | I7: =SUMIF(Trips!$B$2:$B$2000,B7,Trips!$I$2:$I$2000) -> 120 | J7: =IFERROR(H7/E7,0) -> 90 | K7: =SUMIF(Trips!$B$2:$B$2000,B7,Trips!$J$2:$J$2000) -> 210 | L7: =SUMIF(Charging!$B$2:$B$2000,B7,Charging!$E$2:$E$2000) -> 18.9 | M7: =IFERROR(L7/K7,0) -> 0.09 | N7: =SUMIFS(Expenses!$E$2:$E$2000,Expenses!$B$2:$B$2000,B7,Expenses!$C$2:$C$2000,"Loan/Lease Payment")+SUMIFS(Expenses!$E$2:$E$2000,Expenses!$B$2:$B$2000,B7,Expenses!$C$2:$C$2000,"Insurance")+SUMIFS(Expenses!$E$2:$E$2000,Expenses!$B$2:$B$2000,B7,Expenses!$C$2:$C$2000,"Registration/Tax")+SUMIFS(Expenses!$E$2:$E$2000,Expenses!$B$2:$B$2000,B7,Expenses!$C$2:$C$2000,"Subscription (FSD/Connectivity)") -> 850 | O7: =SUMIF(Expenses!$B$2:$B$2000,B7,Expenses!$E$2:$E$2000)-N7 -> 0 | P7: =N7+O7+L7 -> 868.9 | Q7: =H7-P7 -> -508.9 | R7: =IFERROR(Q7/H7,0) -> -1.4136111 | S7: =IFERROR(Q7/C7,0) -> -0.58427095 | T7: =IFERROR(N7/(J7*C7),0) -> 0.01084322
B8: =Vehicles!A3 -> Model Y #2 - Black | C8: =TODAY()-Vehicles!C3 -> 765 | D8: =COUNTIF(Trips!$B$2:$B$2000,B8) -> 0 | E8: =SUMIF(Trips!$B$2:$B$2000,B8,Trips!$F$2:$F$2000) -> 0 | F8: =IFERROR(E8/C8,0) -> 0 | G8: =SUMIF(Trips!$B$2:$B$2000,B8,Trips!$G$2:$G$2000) -> 0 | H8: =SUMIF(Trips!$B$2:$B$2000,B8,Trips!$H$2:$H$2000) -> 0 | I8: =SUMIF(Trips!$B$2:$B$2000,B8,Trips!$I$2:$I$2000) -> 0 | J8: =IFERROR(H8/E8,0) -> 0 | K8: =SUMIF(Trips!$B$2:$B$2000,B8,Trips!$J$2:$J$2000) -> 0 | L8: =SUMIF(Charging!$B$2:$B$2000,B8,Charging!$E$2:$E$2000) -> 0 | M8: =IFERROR(L8/K8,0) -> 0 | N8: =SUMIFS(Expenses!$E$2:$E$2000,Expenses!$B$2:$B$2000,B8,Expenses!$C$2:$C$2000,"Loan/Lease Payment")+SUMIFS(Expenses!$E$2:$E$2000,Expenses!$B$2:$B$2000,B8,Expenses!$C$2:$C$2000,"Insurance")+SUMIFS(Expenses!$E$2:$E$2000,Expenses!$B$2:$B$2000,B8,Expenses!$C$2:$C$2000,"Registration/Tax")+SUMIFS(Expenses!$E$2:$E$2000,Expenses!$B$2:$B$2000,B8,Expenses!$C$2:$C$2000,"Subscription (FSD/Connectivity)") -> 0 | O8: =SUMIF(Expenses!$B$2:$B$2000,B8,Expenses!$E$2:$E$2000)-N8 -> 0 | P8: =N8+O8+L8 -> 0 | Q8: =H8-P8 -> 0 | R8: =IFERROR(Q8/H8,0) -> 0 | S8: =IFERROR(Q8/C8,0) -> 0 | T8: =IFERROR(N8/(J8*C8),0) -> 0
B9: Fleet Total | C9: =SUM(C7:C8) -> 1636 | D9: =SUM(D7:D8) -> 1 | E9: =SUM(E7:E8) -> 4 | F9: =IFERROR(E9/C9,0) -> 0.0024449878 | G9: =SUM(G7:G8) -> 480 | H9: =SUM(H7:H8) -> 360 | I9: =SUM(I7:I8) -> 120 | J9: =IFERROR(H9/E9,0) -> 90 | K9: =SUM(K7:K8) -> 210 | L9: =SUM(L7:L8) -> 18.9 | M9: =IFERROR(L9/K9,0) -> 0.09 | N9: =SUM(N7:N8) -> 850 | O9: =SUM(O7:O8) -> 0 | P9: =SUM(P7:P8) -> 868.9 | Q9: =SUM(Q7:Q8) -> -508.9 | R9: =IFERROR(Q9/H9,0) -> -1.4136111 | S9: =IFERROR(Q9/C9,0) -> -0.31106357 | T9: =IFERROR(N9/(J9*C9),0) -> 0.0057728878
B11: OPERATIONAL ALERTS
B12: Vehicle | C12: Alert | D12: Detail | E12: Status
B13: =Vehicles!A2 -> Model Y #1 - White | C13: Insurance Renewal | D13: =B13&" renews "&TEXT(Vehicles!O2,"mmm d, yyyy")&" ("&(Vehicles!O2-TODAY())&" days)" -> Model Y #1 - White renews Mar 1, 2027 (224 days) | E13: =IF(Vehicles!O2-TODAY()<60,"Renew Soon","OK") -> OK
B14: =Vehicles!A3 -> Model Y #2 - Black | C14: Insurance Renewal | D14: =B14&" renews "&TEXT(Vehicles!O3,"mmm d, yyyy")&" ("&(Vehicles!O3-TODAY())&" days)" -> Model Y #2 - Black renews Jun 15, 2027 (330 days) | E14: =IF(Vehicles!O3-TODAY()<60,"Renew Soon","OK") -> OK
B15: =Vehicles!A2 -> Model Y #1 - White | C15: Registration Renewal | D15: =B15&" renews "&TEXT(Vehicles!P2,"mmm d, yyyy")&" ("&(Vehicles!P2-TODAY())&" days)" -> Model Y #1 - White renews Mar 1, 2027 (224 days) | E15: =IF(Vehicles!P2-TODAY()<60,"Renew Soon","OK") -> OK
B16: =Vehicles!A3 -> Model Y #2 - Black | C16: Registration Renewal | D16: =B16&" renews "&TEXT(Vehicles!P3,"mmm d, yyyy")&" ("&(Vehicles!P3-TODAY())&" days)" -> Model Y #2 - Black renews Jun 15, 2027 (330 days) | E16: =IF(Vehicles!P3-TODAY()<60,"Renew Soon","OK") -> OK
B17: =Vehicles!A2 -> Model Y #1 - White | C17: Maintenance Due | D17: =(Vehicles!L2-Vehicles!K2)&" mi until next service" -> 6500 mi until next service | E17: =IF(Vehicles!L2-Vehicles!K2<1000,"Due Soon","OK") -> OK
B18: =Vehicles!A3 -> Model Y #2 - Black | C18: Maintenance Due | D18: =(Vehicles!L3-Vehicles!K3)&" mi until next service" -> 9000 mi until next service | E18: =IF(Vehicles!L3-Vehicles!K3<1000,"Due Soon","OK") -> OK
B19: =Vehicles!A2 -> Model Y #1 - White | C19: Utilization | D19: =TEXT(F7,"0.0%")&" of available days booked" -> 0.5% of available days booked | E19: =IF(F7<0.4,"Low Utilization","Healthy") -> Low Utilization
B20: =Vehicles!A3 -> Model Y #2 - Black | C20: Utilization | D20: =TEXT(F8,"0.0%")&" of available days booked" -> 0.0% of available days booked | E20: =IF(F8<0.4,"Low Utilization","Healthy") -> Low Utilization
B21: =Vehicles!A2 -> Model Y #1 - White | C21: Profitability | D21: =TEXT(R7,"0.0%")&" net margin" -> -141.4% net margin | E21: =IF(R7<0,"Losing Money",IF(R7<0.15,"Thin Margin","Healthy")) -> Losing Money
B22: =Vehicles!A3 -> Model Y #2 - Black | C22: Profitability | D22: =TEXT(R8,"0.0%")&" net margin" -> 0.0% net margin | E22: =IF(R8<0,"Losing Money",IF(R8<0.15,"Thin Margin","Healthy")) -> Thin Margin
B24: MONTHLY TREND (trailing 12 months)
B26: Month | C26: Month Label | D26: MonthKey | E26: V1 Net Earnings | F26: V1 Costs | G26: V1 Profit | H26: V1 Utilization % | I26: V2 Net Earnings | J26: V2 Costs | K26: V2 Profit | L26: V2 Utilization % | M26: Fleet Net Earnings | N26: Fleet Costs | O26: Fleet Profit | P26: Fleet Utilization %
B27: =EDATE(TODAY(),-11) -> 45889 | C27: =TEXT(B27,"mmm-yy") -> Aug-25 | D27: =TEXT(B27,"yyyy-mm") -> 2025-08 | E27: =SUMIFS(Trips!$H$2:$H$2000,Trips!$B$2:$B$2000,$B$7,Trips!$L$2:$L$2000,D27) -> 0 | F27: =SUMIFS(Expenses!$E$2:$E$2000,Expenses!$B$2:$B$2000,$B$7,Expenses!$F$2:$F$2000,D27)+SUMIFS(Charging!$E$2:$E$2000,Charging!$B$2:$B$2000,$B$7,Charging!$H$2:$H$2000,D27) -> 0 | G27: =E27-F27 -> 0 | H27: =IFERROR(SUMIFS(Trips!$F$2:$F$2000,Trips!$B$2:$B$2000,$B$7,Trips!$L$2:$L$2000,D27)/DAY(EOMONTH(B27,0)),0) -> 0 | I27: =SUMIFS(Trips!$H$2:$H$2000,Trips!$B$2:$B$2000,$B$8,Trips!$L$2:$L$2000,D27) -> 0 | J27: =SUMIFS(Expenses!$E$2:$E$2000,Expenses!$B$2:$B$2000,$B$8,Expenses!$F$2:$F$2000,D27)+SUMIFS(Charging!$E$2:$E$2000,Charging!$B$2:$B$2000,$B$8,Charging!$H$2:$H$2000,D27) -> 0 | K27: =I27-J27 -> 0 | L27: =IFERROR(SUMIFS(Trips!$F$2:$F$2000,Trips!$B$2:$B$2000,$B$8,Trips!$L$2:$L$2000,D27)/DAY(EOMONTH(B27,0)),0) -> 0 | M27: =E27+I27 -> 0 | N27: =F27+J27 -> 0 | O27: =G27+K27 -> 0 | P27: =IFERROR(SUMIFS(Trips!$F$2:$F$2000,Trips!$L$2:$L$2000,D27)/(COUNTA(Vehicles!$A$2:$A$50)*DAY(EOMONTH(B27,0))),0) -> 0
B28: =EDATE(B27,1) -> 45920 | C28: =TEXT(B28,"mmm-yy") -> Sep-25 | D28: =TEXT(B28,"yyyy-mm") -> 2025-09 | E28: =SUMIFS(Trips!$H$2:$H$2000,Trips!$B$2:$B$2000,$B$7,Trips!$L$2:$L$2000,D28) -> 0 | F28: =SUMIFS(Expenses!$E$2:$E$2000,Expenses!$B$2:$B$2000,$B$7,Expenses!$F$2:$F$2000,D28)+SUMIFS(Charging!$E$2:$E$2000,Charging!$B$2:$B$2000,$B$7,Charging!$H$2:$H$2000,D28) -> 0 | G28: =E28-F28 -> 0 | H28: =IFERROR(SUMIFS(Trips!$F$2:$F$2000,Trips!$B$2:$B$2000,$B$7,Trips!$L$2:$L$2000,D28)/DAY(EOMONTH(B28,0)),0) -> 0 | I28: =SUMIFS(Trips!$H$2:$H$2000,Trips!$B$2:$B$2000,$B$8,Trips!$L$2:$L$2000,D28) -> 0 | J28: =SUMIFS(Expenses!$E$2:$E$2000,Expenses!$B$2:$B$2000,$B$8,Expenses!$F$2:$F$2000,D28)+SUMIFS(Charging!$E$2:$E$2000,Charging!$B$2:$B$2000,$B$8,Charging!$H$2:$H$2000,D28) -> 0 | K28: =I28-J28 -> 0 | L28: =IFERROR(SUMIFS(Trips!$F$2:$F$2000,Trips!$B$2:$B$2000,$B$8,Trips!$L$2:$L$2000,D28)/DAY(EOMONTH(B28,0)),0) -> 0 | M28: =E28+I28 -> 0 | N28: =F28+J28 -> 0 | O28: =G28+K28 -> 0 | P28: =IFERROR(SUMIFS(Trips!$F$2:$F$2000,Trips!$L$2:$L$2000,D28)/(COUNTA(Vehicles!$A$2:$A$50)*DAY(EOMONTH(B28,0))),0) -> 0
B29: =EDATE(B28,1) -> 45950 | C29: =TEXT(B29,"mmm-yy") -> Oct-25 | D29: =TEXT(B29,"yyyy-mm") -> 2025-10 | E29: =SUMIFS(Trips!$H$2:$H$2000,Trips!$B$2:$B$2000,$B$7,Trips!$L$2:$L$2000,D29) -> 0 | F29: =SUMIFS(Expenses!$E$2:$E$2000,Expenses!$B$2:$B$2000,$B$7,Expenses!$F$2:$F$2000,D29)+SUMIFS(Charging!$E$2:$E$2000,Charging!$B$2:$B$2000,$B$7,Charging!$H$2:$H$2000,D29) -> 0 | G29: =E29-F29 -> 0 | H29: =IFERROR(SUMIFS(Trips!$F$2:$F$2000,Trips!$B$2:$B$2000,$B$7,Trips!$L$2:$L$2000,D29)/DAY(EOMONTH(B29,0)),0) -> 0 | I29: =SUMIFS(Trips!$H$2:$H$2000,Trips!$B$2:$B$2000,$B$8,Trips!$L$2:$L$2000,D29) -> 0 | J29: =SUMIFS(Expenses!$E$2:$E$2000,Expenses!$B$2:$B$2000,$B$8,Expenses!$F$2:$F$2000,D29)+SUMIFS(Charging!$E$2:$E$2000,Charging!$B$2:$B$2000,$B$8,Charging!$H$2:$H$2000,D29) -> 0 | K29: =I29-J29 -> 0 | L29: =IFERROR(SUMIFS(Trips!$F$2:$F$2000,Trips!$B$2:$B$2000,$B$8,Trips!$L$2:$L$2000,D29)/DAY(EOMONTH(B29,0)),0) -> 0 | M29: =E29+I29 -> 0 | N29: =F29+J29 -> 0 | O29: =G29+K29 -> 0 | P29: =IFERROR(SUMIFS(Trips!$F$2:$F$2000,Trips!$L$2:$L$2000,D29)/(COUNTA(Vehicles!$A$2:$A$50)*DAY(EOMONTH(B29,0))),0) -> 0
B30: =EDATE(B29,1) -> 45981 | C30: =TEXT(B30,"mmm-yy") -> Nov-25 | D30: =TEXT(B30,"yyyy-mm") -> 2025-11 | E30: =SUMIFS(Trips!$H$2:$H$2000,Trips!$B$2:$B$2000,$B$7,Trips!$L$2:$L$2000,D30) -> 0 | F30: =SUMIFS(Expenses!$E$2:$E$2000,Expenses!$B$2:$B$2000,$B$7,Expenses!$F$2:$F$2000,D30)+SUMIFS(Charging!$E$2:$E$2000,Charging!$B$2:$B$2000,$B$7,Charging!$H$2:$H$2000,D30) -> 0 | G30: =E30-F30 -> 0 | H30: =IFERROR(SUMIFS(Trips!$F$2:$F$2000,Trips!$B$2:$B$2000,$B$7,Trips!$L$2:$L$2000,D30)/DAY(EOMONTH(B30,0)),0) -> 0 | I30: =SUMIFS(Trips!$H$2:$H$2000,Trips!$B$2:$B$2000,$B$8,Trips!$L$2:$L$2000,D30) -> 0 | J30: =SUMIFS(Expenses!$E$2:$E$2000,Expenses!$B$2:$B$2000,$B$8,Expenses!$F$2:$F$2000,D30)+SUMIFS(Charging!$E$2:$E$2000,Charging!$B$2:$B$2000,$B$8,Charging!$H$2:$H$2000,D30) -> 0 | K30: =I30-J30 -> 0 | L30: =IFERROR(SUMIFS(Trips!$F$2:$F$2000,Trips!$B$2:$B$2000,$B$8,Trips!$L$2:$L$2000,D30)/DAY(EOMONTH(B30,0)),0) -> 0 | M30: =E30+I30 -> 0 | N30: =F30+J30 -> 0 | O30: =G30+K30 -> 0 | P30: =IFERROR(SUMIFS(Trips!$F$2:$F$2000,Trips!$L$2:$L$2000,D30)/(COUNTA(Vehicles!$A$2:$A$50)*DAY(EOMONTH(B30,0))),0) -> 0
B31: =EDATE(B30,1) -> 46011 | C31: =TEXT(B31,"mmm-yy") -> Dec-25 | D31: =TEXT(B31,"yyyy-mm") -> 2025-12 | E31: =SUMIFS(Trips!$H$2:$H$2000,Trips!$B$2:$B$2000,$B$7,Trips!$L$2:$L$2000,D31) -> 0 | F31: =SUMIFS(Expenses!$E$2:$E$2000,Expenses!$B$2:$B$2000,$B$7,Expenses!$F$2:$F$2000,D31)+SUMIFS(Charging!$E$2:$E$2000,Charging!$B$2:$B$2000,$B$7,Charging!$H$2:$H$2000,D31) -> 0 | G31: =E31-F31 -> 0 | H31: =IFERROR(SUMIFS(Trips!$F$2:$F$2000,Trips!$B$2:$B$2000,$B$7,Trips!$L$2:$L$2000,D31)/DAY(EOMONTH(B31,0)),0) -> 0 | I31: =SUMIFS(Trips!$H$2:$H$2000,Trips!$B$2:$B$2000,$B$8,Trips!$L$2:$L$2000,D31) -> 0 | J31: =SUMIFS(Expenses!$E$2:$E$2000,Expenses!$B$2:$B$2000,$B$8,Expenses!$F$2:$F$2000,D31)+SUMIFS(Charging!$E$2:$E$2000,Charging!$B$2:$B$2000,$B$8,Charging!$H$2:$H$2000,D31) -> 0 | K31: =I31-J31 -> 0 | L31: =IFERROR(SUMIFS(Trips!$F$2:$F$2000,Trips!$B$2:$B$2000,$B$8,Trips!$L$2:$L$2000,D31)/DAY(EOMONTH(B31,0)),0) -> 0 | M31: =E31+I31 -> 0 | N31: =F31+J31 -> 0 | O31: =G31+K31 -> 0 | P31: =IFERROR(SUMIFS(Trips!$F$2:$F$2000,Trips!$L$2:$L$2000,D31)/(COUNTA(Vehicles!$A$2:$A$50)*DAY(EOMONTH(B31,0))),0) -> 0
B32: =EDATE(B31,1) -> 46042 | C32: =TEXT(B32,"mmm-yy") -> Jan-26 | D32: =TEXT(B32,"yyyy-mm") -> 2026-01 | E32: =SUMIFS(Trips!$H$2:$H$2000,Trips!$B$2:$B$2000,$B$7,Trips!$L$2:$L$2000,D32) -> 0 | F32: =SUMIFS(Expenses!$E$2:$E$2000,Expenses!$B$2:$B$2000,$B$7,Expenses!$F$2:$F$2000,D32)+SUMIFS(Charging!$E$2:$E$2000,Charging!$B$2:$B$2000,$B$7,Charging!$H$2:$H$2000,D32) -> 0 | G32: =E32-F32 -> 0 | H32: =IFERROR(SUMIFS(Trips!$F$2:$F$2000,Trips!$B$2:$B$2000,$B$7,Trips!$L$2:$L$2000,D32)/DAY(EOMONTH(B32,0)),0) -> 0 | I32: =SUMIFS(Trips!$H$2:$H$2000,Trips!$B$2:$B$2000,$B$8,Trips!$L$2:$L$2000,D32) -> 0 | J32: =SUMIFS(Expenses!$E$2:$E$2000,Expenses!$B$2:$B$2000,$B$8,Expenses!$F$2:$F$2000,D32)+SUMIFS(Charging!$E$2:$E$2000,Charging!$B$2:$B$2000,$B$8,Charging!$H$2:$H$2000,D32) -> 0 | K32: =I32-J32 -> 0 | L32: =IFERROR(SUMIFS(Trips!$F$2:$F$2000,Trips!$B$2:$B$2000,$B$8,Trips!$L$2:$L$2000,D32)/DAY(EOMONTH(B32,0)),0) -> 0 | M32: =E32+I32 -> 0 | N32: =F32+J32 -> 0 | O32: =G32+K32 -> 0 | P32: =IFERROR(SUMIFS(Trips!$F$2:$F$2000,Trips!$L$2:$L$2000,D32)/(COUNTA(Vehicles!$A$2:$A$50)*DAY(EOMONTH(B32,0))),0) -> 0
B33: =EDATE(B32,1) -> 46073 | C33: =TEXT(B33,"mmm-yy") -> Feb-26 | D33: =TEXT(B33,"yyyy-mm") -> 2026-02 | E33: =SUMIFS(Trips!$H$2:$H$2000,Trips!$B$2:$B$2000,$B$7,Trips!$L$2:$L$2000,D33) -> 0 | F33: =SUMIFS(Expenses!$E$2:$E$2000,Expenses!$B$2:$B$2000,$B$7,Expenses!$F$2:$F$2000,D33)+SUMIFS(Charging!$E$2:$E$2000,Charging!$B$2:$B$2000,$B$7,Charging!$H$2:$H$2000,D33) -> 0 | G33: =E33-F33 -> 0 | H33: =IFERROR(SUMIFS(Trips!$F$2:$F$2000,Trips!$B$2:$B$2000,$B$7,Trips!$L$2:$L$2000,D33)/DAY(EOMONTH(B33,0)),0) -> 0 | I33: =SUMIFS(Trips!$H$2:$H$2000,Trips!$B$2:$B$2000,$B$8,Trips!$L$2:$L$2000,D33) -> 0 | J33: =SUMIFS(Expenses!$E$2:$E$2000,Expenses!$B$2:$B$2000,$B$8,Expenses!$F$2:$F$2000,D33)+SUMIFS(Charging!$E$2:$E$2000,Charging!$B$2:$B$2000,$B$8,Charging!$H$2:$H$2000,D33) -> 0 | K33: =I33-J33 -> 0 | L33: =IFERROR(SUMIFS(Trips!$F$2:$F$2000,Trips!$B$2:$B$2000,$B$8,Trips!$L$2:$L$2000,D33)/DAY(EOMONTH(B33,0)),0) -> 0 | M33: =E33+I33 -> 0 | N33: =F33+J33 -> 0 | O33: =G33+K33 -> 0 | P33: =IFERROR(SUMIFS(Trips!$F$2:$F$2000,Trips!$L$2:$L$2000,D33)/(COUNTA(Vehicles!$A$2:$A$50)*DAY(EOMONTH(B33,0))),0) -> 0
B34: =EDATE(B33,1) -> 46101 | C34: =TEXT(B34,"mmm-yy") -> Mar-26 | D34: =TEXT(B34,"yyyy-mm") -> 2026-03 | E34: =SUMIFS(Trips!$H$2:$H$2000,Trips!$B$2:$B$2000,$B$7,Trips!$L$2:$L$2000,D34) -> 0 | F34: =SUMIFS(Expenses!$E$2:$E$2000,Expenses!$B$2:$B$2000,$B$7,Expenses!$F$2:$F$2000,D34)+SUMIFS(Charging!$E$2:$E$2000,Charging!$B$2:$B$2000,$B$7,Charging!$H$2:$H$2000,D34) -> 0 | G34: =E34-F34 -> 0 | H34: =IFERROR(SUMIFS(Trips!$F$2:$F$2000,Trips!$B$2:$B$2000,$B$7,Trips!$L$2:$L$2000,D34)/DAY(EOMONTH(B34,0)),0) -> 0 | I34: =SUMIFS(Trips!$H$2:$H$2000,Trips!$B$2:$B$2000,$B$8,Trips!$L$2:$L$2000,D34) -> 0 | J34: =SUMIFS(Expenses!$E$2:$E$2000,Expenses!$B$2:$B$2000,$B$8,Expenses!$F$2:$F$2000,D34)+SUMIFS(Charging!$E$2:$E$2000,Charging!$B$2:$B$2000,$B$8,Charging!$H$2:$H$2000,D34) -> 0 | K34: =I34-J34 -> 0 | L34: =IFERROR(SUMIFS(Trips!$F$2:$F$2000,Trips!$B$2:$B$2000,$B$8,Trips!$L$2:$L$2000,D34)/DAY(EOMONTH(B34,0)),0) -> 0 | M34: =E34+I34 -> 0 | N34: =F34+J34 -> 0 | O34: =G34+K34 -> 0 | P34: =IFERROR(SUMIFS(Trips!$F$2:$F$2000,Trips!$L$2:$L$2000,D34)/(COUNTA(Vehicles!$A$2:$A$50)*DAY(EOMONTH(B34,0))),0) -> 0
B35: =EDATE(B34,1) -> 46132 | C35: =TEXT(B35,"mmm-yy") -> Apr-26 | D35: =TEXT(B35,"yyyy-mm") -> 2026-04 | E35: =SUMIFS(Trips!$H$2:$H$2000,Trips!$B$2:$B$2000,$B$7,Trips!$L$2:$L$2000,D35) -> 0 | F35: =SUMIFS(Expenses!$E$2:$E$2000,Expenses!$B$2:$B$2000,$B$7,Expenses!$F$2:$F$2000,D35)+SUMIFS(Charging!$E$2:$E$2000,Charging!$B$2:$B$2000,$B$7,Charging!$H$2:$H$2000,D35) -> 0 | G35: =E35-F35 -> 0 | H35: =IFERROR(SUMIFS(Trips!$F$2:$F$2000,Trips!$B$2:$B$2000,$B$7,Trips!$L$2:$L$2000,D35)/DAY(EOMONTH(B35,0)),0) -> 0 | I35: =SUMIFS(Trips!$H$2:$H$2000,Trips!$B$2:$B$2000,$B$8,Trips!$L$2:$L$2000,D35) -> 0 | J35: =SUMIFS(Expenses!$E$2:$E$2000,Expenses!$B$2:$B$2000,$B$8,Expenses!$F$2:$F$2000,D35)+SUMIFS(Charging!$E$2:$E$2000,Charging!$B$2:$B$2000,$B$8,Charging!$H$2:$H$2000,D35) -> 0 | K35: =I35-J35 -> 0 | L35: =IFERROR(SUMIFS(Trips!$F$2:$F$2000,Trips!$B$2:$B$2000,$B$8,Trips!$L$2:$L$2000,D35)/DAY(EOMONTH(B35,0)),0) -> 0 | M35: =E35+I35 -> 0 | N35: =F35+J35 -> 0 | O35: =G35+K35 -> 0 | P35: =IFERROR(SUMIFS(Trips!$F$2:$F$2000,Trips!$L$2:$L$2000,D35)/(COUNTA(Vehicles!$A$2:$A$50)*DAY(EOMONTH(B35,0))),0) -> 0
B36: =EDATE(B35,1) -> 46162 | C36: =TEXT(B36,"mmm-yy") -> May-26 | D36: =TEXT(B36,"yyyy-mm") -> 2026-05 | E36: =SUMIFS(Trips!$H$2:$H$2000,Trips!$B$2:$B$2000,$B$7,Trips!$L$2:$L$2000,D36) -> 0 | F36: =SUMIFS(Expenses!$E$2:$E$2000,Expenses!$B$2:$B$2000,$B$7,Expenses!$F$2:$F$2000,D36)+SUMIFS(Charging!$E$2:$E$2000,Charging!$B$2:$B$2000,$B$7,Charging!$H$2:$H$2000,D36) -> 0 | G36: =E36-F36 -> 0 | H36: =IFERROR(SUMIFS(Trips!$F$2:$F$2000,Trips!$B$2:$B$2000,$B$7,Trips!$L$2:$L$2000,D36)/DAY(EOMONTH(B36,0)),0) -> 0 | I36: =SUMIFS(Trips!$H$2:$H$2000,Trips!$B$2:$B$2000,$B$8,Trips!$L$2:$L$2000,D36) -> 0 | J36: =SUMIFS(Expenses!$E$2:$E$2000,Expenses!$B$2:$B$2000,$B$8,Expenses!$F$2:$F$2000,D36)+SUMIFS(Charging!$E$2:$E$2000,Charging!$B$2:$B$2000,$B$8,Charging!$H$2:$H$2000,D36) -> 0 | K36: =I36-J36 -> 0 | L36: =IFERROR(SUMIFS(Trips!$F$2:$F$2000,Trips!$B$2:$B$2000,$B$8,Trips!$L$2:$L$2000,D36)/DAY(EOMONTH(B36,0)),0) -> 0 | M36: =E36+I36 -> 0 | N36: =F36+J36 -> 0 | O36: =G36+K36 -> 0 | P36: =IFERROR(SUMIFS(Trips!$F$2:$F$2000,Trips!$L$2:$L$2000,D36)/(COUNTA(Vehicles!$A$2:$A$50)*DAY(EOMONTH(B36,0))),0) -> 0
B37: =EDATE(B36,1) -> 46193 | C37: =TEXT(B37,"mmm-yy") -> Jun-26 | D37: =TEXT(B37,"yyyy-mm") -> 2026-06 | E37: =SUMIFS(Trips!$H$2:$H$2000,Trips!$B$2:$B$2000,$B$7,Trips!$L$2:$L$2000,D37) -> 360 | F37: =SUMIFS(Expenses!$E$2:$E$2000,Expenses!$B$2:$B$2000,$B$7,Expenses!$F$2:$F$2000,D37)+SUMIFS(Charging!$E$2:$E$2000,Charging!$B$2:$B$2000,$B$7,Charging!$H$2:$H$2000,D37) -> 868.9 | G37: =E37-F37 -> -508.9 | H37: =IFERROR(SUMIFS(Trips!$F$2:$F$2000,Trips!$B$2:$B$2000,$B$7,Trips!$L$2:$L$2000,D37)/DAY(EOMONTH(B37,0)),0) -> 0.13333333 | I37: =SUMIFS(Trips!$H$2:$H$2000,Trips!$B$2:$B$2000,$B$8,Trips!$L$2:$L$2000,D37) -> 0 | J37: =SUMIFS(Expenses!$E$2:$E$2000,Expenses!$B$2:$B$2000,$B$8,Expenses!$F$2:$F$2000,D37)+SUMIFS(Charging!$E$2:$E$2000,Charging!$B$2:$B$2000,$B$8,Charging!$H$2:$H$2000,D37) -> 0 | K37: =I37-J37 -> 0 | L37: =IFERROR(SUMIFS(Trips!$F$2:$F$2000,Trips!$B$2:$B$2000,$B$8,Trips!$L$2:$L$2000,D37)/DAY(EOMONTH(B37,0)),0) -> 0 | M37: =E37+I37 -> 360 | N37: =F37+J37 -> 868.9 | O37: =G37+K37 -> -508.9 | P37: =IFERROR(SUMIFS(Trips!$F$2:$F$2000,Trips!$L$2:$L$2000,D37)/(COUNTA(Vehicles!$A$2:$A$50)*DAY(EOMONTH(B37,0))),0) -> 0.066666667
B38: =EDATE(B37,1) -> 46223 | C38: =TEXT(B38,"mmm-yy") -> Jul-26 | D38: =TEXT(B38,"yyyy-mm") -> 2026-07 | E38: =SUMIFS(Trips!$H$2:$H$2000,Trips!$B$2:$B$2000,$B$7,Trips!$L$2:$L$2000,D38) -> 0 | F38: =SUMIFS(Expenses!$E$2:$E$2000,Expenses!$B$2:$B$2000,$B$7,Expenses!$F$2:$F$2000,D38)+SUMIFS(Charging!$E$2:$E$2000,Charging!$B$2:$B$2000,$B$7,Charging!$H$2:$H$2000,D38) -> 0 | G38: =E38-F38 -> 0 | H38: =IFERROR(SUMIFS(Trips!$F$2:$F$2000,Trips!$B$2:$B$2000,$B$7,Trips!$L$2:$L$2000,D38)/DAY(EOMONTH(B38,0)),0) -> 0 | I38: =SUMIFS(Trips!$H$2:$H$2000,Trips!$B$2:$B$2000,$B$8,Trips!$L$2:$L$2000,D38) -> 0 | J38: =SUMIFS(Expenses!$E$2:$E$2000,Expenses!$B$2:$B$2000,$B$8,Expenses!$F$2:$F$2000,D38)+SUMIFS(Charging!$E$2:$E$2000,Charging!$B$2:$B$2000,$B$8,Charging!$H$2:$H$2000,D38) -> 0 | K38: =I38-J38 -> 0 | L38: =IFERROR(SUMIFS(Trips!$F$2:$F$2000,Trips!$B$2:$B$2000,$B$8,Trips!$L$2:$L$2000,D38)/DAY(EOMONTH(B38,0)),0) -> 0 | M38: =E38+I38 -> 0 | N38: =F38+J38 -> 0 | O38: =G38+K38 -> 0 | P38: =IFERROR(SUMIFS(Trips!$F$2:$F$2000,Trips!$L$2:$L$2000,D38)/(COUNTA(Vehicles!$A$2:$A$50)*DAY(EOMONTH(B38,0))),0) -> 0
